formextension.py
formextension-1.0.dist-info/LICENSE
formextension-1.0.dist-info/METADATA
formextension-1.0.dist-info/WHEEL
formextension-1.0.dist-info/top_level.txt
formextension-1.0.dist-info/RECORD
