Metadata-Version: 2.1
Name: formextension
Version: 1.0
Summary: UNKNOWN
Home-page: https://github.com/Mrostgaard/Form-MarkdownExtension
Author: Mark Rostgaard
Author-email: mrostgaard@protonmail.com
License: UNKNOWN
Platform: UNKNOWN
Requires-Dist: markdown (>=3.0)
